LDVisualization/__init__.py
LDVisualization/const.py
LDVisualization/inputHandlers.py
LDVisualization/utils.py
LDVisualization/visualize.py
ldvisualization_alan1321-0.0.2.dist-info/METADATA
ldvisualization_alan1321-0.0.2.dist-info/WHEEL
ldvisualization_alan1321-0.0.2.dist-info/licenses/LICENSE
ldvisualization_alan1321-0.0.2.dist-info/RECORD
